bluer_flow/README.py
bluer_flow/__init__.py
bluer_flow/__main__.py
bluer_flow/config.env
bluer_flow/env.py
bluer_flow/host.py
bluer_flow/logger.py
bluer_flow/sample.env
bluer_flow/urls.py
bluer_flow/.abcli/actions.sh
bluer_flow/.abcli/alias.sh
bluer_flow/.abcli/bluer_flow.sh
bluer_flow/.abcli/localflow.sh
bluer_flow/.abcli/workflow.sh
bluer_flow/.abcli/localflow/eval.sh
bluer_flow/.abcli/localflow/list.sh
bluer_flow/.abcli/localflow/rm.sh
bluer_flow/.abcli/localflow/start.sh
bluer_flow/.abcli/localflow/stop.sh
bluer_flow/.abcli/tests/README.sh
bluer_flow/.abcli/tests/help.sh
bluer_flow/.abcli/tests/localflow_eval.sh
bluer_flow/.abcli/tests/localflow_list.sh
bluer_flow/.abcli/tests/localflow_stop.sh
bluer_flow/.abcli/tests/version.sh
bluer_flow/.abcli/tests/workflow_runner.sh
bluer_flow/.abcli/workflow/config.sh
bluer_flow/.abcli/workflow/create.sh
bluer_flow/.abcli/workflow/monitor.sh
bluer_flow/.abcli/workflow/submit.sh
bluer_flow/help/__init__.py
bluer_flow/help/__main__.py
bluer_flow/help/functions.py
bluer_flow/help/localflow.py
bluer_flow/help/workflow.py
bluer_flow/workflow/README.py
bluer_flow/workflow/__init__.py
bluer_flow/workflow/__main__.py
bluer_flow/workflow/dot_file.py
bluer_flow/workflow/generic.py
bluer_flow/workflow/patterns/__init__.py
bluer_flow/workflow/patterns/__main__.py
bluer_flow/workflow/patterns/a-bc-d.dot
bluer_flow/workflow/patterns/hourglass.dot
bluer_flow/workflow/patterns/map-reduce-large.dot
bluer_flow/workflow/patterns/map-reduce.dot
bluer_flow/workflow/runners/__init__.py
bluer_flow/workflow/runners/__main__.py
bluer_flow/workflow/runners/factory.py
bluer_flow/workflow/runners/generic.py
bluer_flow/workflow/runners/local.py
bluer_flow-5.57.1.dist-info/licenses/LICENSE
bluer_flow-5.57.1.dist-info/METADATA
bluer_flow-5.57.1.dist-info/WHEEL
bluer_flow-5.57.1.dist-info/top_level.txt
bluer_flow-5.57.1.dist-info/RECORD
