Metadata-Version: 2.4
Name: bluer_flow
Version: 5.57.1
Summary: 📜 Workflow management.
Home-page: https://github.com/kamangir/bluer-flow
Author: Arash Abadpour (Kamangir)
Author-email: arash.abadpour@gmail.com
License: CC0-1.0
Classifier: Programming Language :: Python :: 3
Classifier: Programming Language :: Unix Shell
Classifier: Operating System :: OS Independent
License-File: LICENSE
Requires-Dist: bluer_ai
Requires-Dist: beautifulsoup4
Requires-Dist: networkx
Requires-Dist: opencv-python
Requires-Dist: pydot==3.0.4
Requires-Dist: requests
Dynamic: author
Dynamic: author-email
Dynamic: classifier
Dynamic: description
Dynamic: description-content-type
Dynamic: home-page
Dynamic: license
Dynamic: license-file
Dynamic: requires-dist
Dynamic: summary
